matheel/__init__.py
matheel/cli.py
matheel/similarity.py
matheel-0.1.8.dist-info/licenses/LICENSE
matheel-0.1.8.dist-info/METADATA
matheel-0.1.8.dist-info/WHEEL
matheel-0.1.8.dist-info/entry_points.txt
matheel-0.1.8.dist-info/top_level.txt
matheel-0.1.8.dist-info/RECORD
