Metadata-Version: 2.4
Name: matheel
Version: 0.1.8
Summary: Matheel: A CLI and Python package for source-code similarity detection.
Author: Fahad Ebrahim
License-Expression: CC-BY-NC-4.0
Project-URL: Homepage, https://github.com/FahadEbrahim/matheel
Project-URL: Source, https://github.com/FahadEbrahim/matheel
Requires-Python: >=3.9
License-File: LICENSE
Requires-Dist: click
Requires-Dist: pandas
Requires-Dist: numpy
Requires-Dist: rapidfuzz
Requires-Dist: sentence-transformers
Requires-Dist: sentencepiece
Dynamic: license-file
